cloudaux/__about__.py
cloudaux/__init__.py
cloudaux/aws/__init__.py
cloudaux/aws/decorators.py
cloudaux/aws/sts.py
cloudaux_lite-1.0.0.dist-info/AUTHORS
cloudaux_lite-1.0.0.dist-info/LICENSE
cloudaux_lite-1.0.0.dist-info/METADATA
cloudaux_lite-1.0.0.dist-info/WHEEL
cloudaux_lite-1.0.0.dist-info/top_level.txt
cloudaux_lite-1.0.0.dist-info/RECORD
