Metadata-Version: 2.1
Name: cloudaux-lite
Version: 1.0.0
Summary: Cloud Auxiliary (lite) is a python wrapper and orchestration module for interacting with cloud providers
Home-page: https://github.com/mikegrima/cloudaux-lite
Author: The Cloudaux Developers
Author-email: mike.r.grima@gmail.com
License: UNKNOWN
Platform: UNKNOWN
Classifier: Programming Language :: Python :: 3
Classifier: Programming Language :: Python :: 3.9
Classifier: Programming Language :: Python :: 3.10
Classifier: Programming Language :: Python :: 3.11
License-File: LICENSE
License-File: AUTHORS
Requires-Dist: boto3
Requires-Dist: botocore
Provides-Extra: dev
Provides-Extra: docs
Provides-Extra: tests
Requires-Dist: pytest ; extra == 'tests'
Requires-Dist: pytest-cov ; extra == 'tests'
Requires-Dist: moto ; extra == 'tests'
Requires-Dist: tox ; extra == 'tests'
